p2tg.py
p2tg-0.2.dist-info/METADATA
p2tg-0.2.dist-info/RECORD
p2tg-0.2.dist-info/WHEEL
p2tg-0.2.dist-info/top_level.txt
